titans_miras/__init__.py
titans_miras/config.py
titans_miras/neural_memory.py
titans_miras/attention/__init__.py
titans_miras/attention/implicit_mlp.py
titans_miras/attention/nested_attention.py
titans_miras/attention/segmented_attention.py
titans_miras/memory/__init__.py
titans_miras/memory/factorized_memory_mlp.py
titans_miras/memory/gated_residual_memory_mlp.py
titans_miras/memory/memory_attention.py
titans_miras/memory/memory_mlp.py
titans_miras/memory/memory_swiglu_mlp.py
titans_miras/miras/__init__.py
titans_miras/miras/bias.py
titans_miras/miras/config.py
titans_miras/miras/retention.py
titans_miras/norm/__init__.py
titans_miras/norm/layer_norm.py
titans_miras/norm/multihead_rms_norm.py
titans_miras/norm/residual_norm.py
titans_miras/shared/__init__.py
titans_miras/shared/utils.py
titans_miras/transformer/__init__.py
titans_miras/transformer/mac_transformer.py
python_titans_miras-0.0.1.dist-info/METADATA
python_titans_miras-0.0.1.dist-info/WHEEL
python_titans_miras-0.0.1.dist-info/licenses/LICENSE
python_titans_miras-0.0.1.dist-info/RECORD
