Metadata-Version: 2.4
Name: python-titans-miras
Version: 0.0.1
Summary: Titans architecture and MIRAS framework for test-time memorization in long-context sequence modeling
Project-URL: Homepage, https://github.com/jonlukewatts/titans-miras
Project-URL: Documentation, https://github.com/jonlukewatts/titans-miras#readme
Project-URL: Repository, https://github.com/jonlukewatts/titans-miras
Project-URL: Issues, https://github.com/jonlukewatts/titans-miras/issues
Author: Titans-MIRAS Contributors
License: MIT License
License-File: LICENSE
Keywords: attention,deep-learning,long-context,miras,neural-memory,pytorch,sequence-modeling,test-time-learning,titans,transformer
Classifier: Development Status :: 4 - Beta
Classifier: Intended Audience :: Developers
Classifier: Intended Audience :: Science/Research
Classifier: License :: OSI Approved :: MIT License
Classifier: Operating System :: OS Independent
Classifier: Programming Language :: Python :: 3.9
Classifier: Programming Language :: Python :: 3.10
Classifier: Programming Language :: Python :: 3.11
Classifier: Programming Language :: Python :: 3.12
Classifier: Topic :: Scientific/Engineering :: Artificial Intelligence
Classifier: Topic :: Scientific/Engineering :: Information Analysis
Requires-Python: >=3.9
Requires-Dist: assoc-scan
Requires-Dist: axial-positional-embedding>=0.3.10
Requires-Dist: einops>=0.8.0
Requires-Dist: einx>=0.3.0
Requires-Dist: hyper-connections>=0.1.11
Requires-Dist: ninja
Requires-Dist: pydantic>=2.0
Requires-Dist: rotary-embedding-torch
Requires-Dist: tensordict
Requires-Dist: torch>=2.0
Requires-Dist: tqdm
Requires-Dist: x-transformers
Provides-Extra: all
Requires-Dist: accelerate; extra == 'all'
Requires-Dist: adam-atan2-pytorch>=0.1.18; extra == 'all'
Requires-Dist: black; extra == 'all'
Requires-Dist: matplotlib; extra == 'all'
Requires-Dist: numpy; extra == 'all'
Requires-Dist: pytest-cov; extra == 'all'
Requires-Dist: pytest>=7.0; extra == 'all'
Requires-Dist: setuptools; extra == 'all'
Requires-Dist: tqdm; extra == 'all'
Requires-Dist: wandb; extra == 'all'
Provides-Extra: dev
Requires-Dist: accelerate; extra == 'dev'
Requires-Dist: adam-atan2-pytorch>=0.1.18; extra == 'dev'
Requires-Dist: black; extra == 'dev'
Requires-Dist: matplotlib; extra == 'dev'
Requires-Dist: numpy; extra == 'dev'
Requires-Dist: setuptools; extra == 'dev'
Requires-Dist: tqdm; extra == 'dev'
Requires-Dist: wandb; extra == 'dev'
Provides-Extra: test
Requires-Dist: pytest-cov; extra == 'test'
Requires-Dist: pytest>=7.0; extra == 'test'
